excoverflow.py
excoverflow-0.1.0.dist-info/DESCRIPTION.rst
excoverflow-0.1.0.dist-info/METADATA
excoverflow-0.1.0.dist-info/RECORD
excoverflow-0.1.0.dist-info/WHEEL
excoverflow-0.1.0.dist-info/metadata.json
excoverflow-0.1.0.dist-info/top_level.txt
