Metadata-Version: 2.0
Name: excoverflow
Version: 0.1.0
Summary: Appends google/stackoverflow search links to unhandled exceptions
Home-page: https://github.com/crflynn/excoverflow
Author: Christopher Flynn
Author-email: crf204@gmail.com
License: MIT
Platform: UNKNOWN
Classifier: License :: OSI Approved :: MIT License
Classifier: Intended Audience :: Developers
Classifier: Topic :: Software Development :: Libraries :: Python Modules
Classifier: Programming Language :: Python
Classifier: Programming Language :: Python :: 2
Classifier: Programming Language :: Python :: 3
Classifier: Programming Language :: Python :: Implementation :: CPython
